{
  "total": 103,
  "updateTime": "2026-07-05T09:10:46.754Z",
  "updateInterval": "6 小时",
  "byType": {
    "vmess": 2,
    "trojan": 19,
    "vless": 82
  },
  "byCountry": {
    "Unknown": 36,
    "HK": 4,
    "JP": 3,
    "SG": 5,
    "US": 28,
    "DE": 19,
    "RU": 4,
    "FR": 1,
    "GB": 2,
    "TW": 1
  },
  "byPort": {
    "80": 21,
    "346": 1,
    "443": 21,
    "446": 1,
    "2008": 1,
    "2082": 2,
    "2086": 1,
    "2098": 1,
    "3743": 1,
    "6357": 1,
    "7009": 1,
    "8080": 4,
    "8443": 12,
    "8880": 22,
    "11035": 1,
    "14005": 1,
    "17005": 1,
    "25567": 1,
    "27826": 1,
    "29449": 1,
    "30807": 1,
    "40000": 1,
    "41421": 1,
    "44265": 1,
    "48738": 1,
    "49277": 1,
    "55973": 1
  }
}