{
  "total": 69,
  "updateTime": "2026-01-12T02:08:49.943Z",
  "updateInterval": "6 小时",
  "byType": {
    "vmess": 19,
    "trojan": 35,
    "vless": 15
  },
  "byCountry": {
    "Unknown": 14,
    "HK": 6,
    "DE": 5,
    "JP": 4,
    "IN": 1,
    "CN": 1,
    "US": 25,
    "KR": 1,
    "CA": 1,
    "SG": 4,
    "GB": 2,
    "RU": 5
  },
  "byPort": {
    "80": 2,
    "81": 1,
    "82": 1,
    "83": 1,
    "84": 1,
    "85": 1,
    "86": 1,
    "87": 1,
    "88": 1,
    "89": 1,
    "180": 1,
    "443": 16,
    "587": 1,
    "1221": 1,
    "2053": 4,
    "2083": 3,
    "2087": 4,
    "2096": 3,
    "3076": 1,
    "3579": 1,
    "3901": 1,
    "4006": 2,
    "4443": 1,
    "5076": 2,
    "8443": 3,
    "9000": 1,
    "11945": 1,
    "15805": 1,
    "18509": 1,
    "30804": 1,
    "30807": 1,
    "31102": 1,
    "31103": 1,
    "33873": 1,
    "35501": 1,
    "35502": 1,
    "42507": 1,
    "47083": 1,
    "59003": 1
  }
}