{
  "total": 67,
  "updateTime": "2025-11-25T01:53:39.282Z",
  "updateInterval": "6 小时",
  "byType": {
    "vmess": 13,
    "trojan": 21,
    "vless": 33
  },
  "byCountry": {
    "Unknown": 28,
    "HK": 4,
    "JP": 4,
    "SG": 3,
    "US": 13,
    "CA": 1,
    "DE": 2,
    "GB": 1,
    "KR": 5,
    "RU": 6
  },
  "byPort": {
    "80": 1,
    "81": 1,
    "82": 1,
    "83": 1,
    "84": 1,
    "85": 1,
    "86": 1,
    "87": 1,
    "88": 1,
    "89": 1,
    "180": 1,
    "443": 27,
    "1691": 1,
    "2053": 6,
    "2145": 1,
    "2569": 1,
    "2760": 1,
    "2890": 1,
    "3093": 1,
    "3169": 1,
    "4054": 1,
    "5553": 1,
    "8443": 3,
    "13502": 1,
    "22222": 1,
    "22223": 1,
    "28190": 1,
    "30809": 1,
    "40721": 1,
    "50001": 5
  }
}