{
  "total": 217,
  "updateTime": "2026-01-25T12:51:58.505Z",
  "updateInterval": "6 小时",
  "byType": {
    "vmess": 22,
    "trojan": 26,
    "vless": 169
  },
  "byCountry": {
    "Unknown": 38,
    "IN": 1,
    "CN": 2,
    "DE": 4,
    "HK": 9,
    "GB": 2,
    "US": 129,
    "JP": 7,
    "TW": 3,
    "SG": 8,
    "FR": 1,
    "RU": 13
  },
  "byPort": {
    "80": 2,
    "81": 1,
    "82": 1,
    "83": 1,
    "84": 1,
    "85": 1,
    "86": 1,
    "87": 1,
    "88": 1,
    "89": 1,
    "180": 1,
    "432": 1,
    "443": 144,
    "544": 1,
    "1691": 1,
    "2053": 8,
    "2087": 1,
    "2096": 3,
    "2762": 1,
    "3159": 1,
    "3423": 1,
    "3901": 1,
    "4006": 1,
    "4443": 1,
    "5076": 2,
    "7426": 1,
    "8080": 2,
    "8443": 10,
    "9000": 1,
    "10001": 1,
    "15310": 1,
    "18581": 1,
    "21486": 1,
    "30807": 1,
    "30824": 1,
    "30836": 1,
    "31102": 1,
    "31103": 1,
    "34606": 1,
    "35501": 1,
    "40130": 1,
    "43528": 1,
    "44000": 1,
    "47051": 1,
    "47083": 2,
    "50121": 1,
    "50511": 1,
    "51191": 1,
    "59003": 1,
    "59152": 3
  }
}