{
  "total": 217,
  "updateTime": "2026-05-25T15:16:59.697Z",
  "updateInterval": "6 小时",
  "byType": {
    "vmess": 18,
    "trojan": 120,
    "vless": 79
  },
  "byCountry": {
    "Unknown": 30,
    "HK": 9,
    "TW": 1,
    "JP": 12,
    "SG": 38,
    "US": 95,
    "RU": 3,
    "DE": 14,
    "KR": 2,
    "FR": 3,
    "CA": 1,
    "GB": 9
  },
  "byPort": {
    "22": 1,
    "74": 2,
    "80": 2,
    "81": 1,
    "82": 1,
    "83": 1,
    "84": 1,
    "85": 1,
    "86": 1,
    "87": 1,
    "88": 1,
    "89": 1,
    "180": 5,
    "443": 80,
    "587": 1,
    "634": 1,
    "1123": 1,
    "1180": 1,
    "2027": 1,
    "2052": 1,
    "2053": 20,
    "2087": 1,
    "2095": 10,
    "2096": 10,
    "2140": 1,
    "2511": 1,
    "2663": 1,
    "3135": 1,
    "4443": 1,
    "6604": 1,
    "7778": 1,
    "8443": 34,
    "8445": 1,
    "8818": 1,
    "8998": 1,
    "10000": 1,
    "10035": 1,
    "10162": 1,
    "10333": 1,
    "10478": 1,
    "11233": 1,
    "11541": 1,
    "11965": 1,
    "16010": 1,
    "16443": 1,
    "16922": 1,
    "17801": 1,
    "22231": 2,
    "26257": 1,
    "26424": 1,
    "28382": 1,
    "30807": 1,
    "32237": 1,
    "36895": 1,
    "40721": 1,
    "46639": 1,
    "50569": 1,
    "51072": 1,
    "53018": 1,
    "55386": 1,
    "58051": 1
  }
}